fooder_cli/__init__.py
fooder_cli/__main__.py
fooder_cli/client.py
fooder_cli/diary.py
fooder_cli/entry.py
fooder_cli/main.py
fooder_cli/meal.py
fooder_cli/product.py
fooder-0.0.4.dist-info/LICENSE
fooder-0.0.4.dist-info/METADATA
fooder-0.0.4.dist-info/WHEEL
fooder-0.0.4.dist-info/entry_points.txt
fooder-0.0.4.dist-info/top_level.txt
fooder-0.0.4.dist-info/RECORD
