Metadata-Version: 2.1
Name: fooder
Version: 0.0.4
Summary: Minimalistic cli diary for tracking calories
Home-page: https://github.com/ickyicky/fooder-cli-client
Author: Piotr Domanski
Author-email: pi.domanski@gmail.com
Classifier: Programming Language :: Python :: 3
Classifier: License :: OSI Approved :: GNU General Public License v3 or later (GPLv3+)
Classifier: Operating System :: OS Independent
Requires-Python: >=3.6
License-File: LICENSE
Requires-Dist: requests
Requires-Dist: datetime
Requires-Dist: pydantic
Requires-Dist: rich
Requires-Dist: pathlib
